{
	"class" : {
		 },
	"instance" : {
		"dt" : "ShoYoshida 9/25/2016 01:18",
		"dt:" : "ShoYoshida 9/25/2016 01:18",
		"ixBug" : "ShoYoshida 9/24/2016 17:12",
		"ixBug:" : "ShoYoshida 9/24/2016 17:12",
		"ixPersonAssignedTo" : "ShoYoshida 9/24/2016 20:28",
		"ixPersonAssignedTo:" : "ShoYoshida 9/24/2016 20:28",
		"ixPersonEditedBy" : "ShoYoshida 9/25/2016 16:16",
		"ixPersonEditedBy:" : "ShoYoshida 9/25/2016 16:16",
		"sEvent" : "ShoYoshida 9/24/2016 15:30",
		"sEvent:" : "ShoYoshida 9/24/2016 15:30",
		"sFixFor" : "ShoYoshida 9/24/2016 15:30",
		"sFixFor:" : "ShoYoshida 9/24/2016 15:30",
		"sProject" : "ShoYoshida 9/24/2016 15:30",
		"sProject:" : "ShoYoshida 9/24/2016 15:30",
		"sStatus" : "ShoYoshida 9/24/2016 20:28",
		"sStatus:" : "ShoYoshida 9/24/2016 20:28",
		"sTitle" : "ShoYoshida 9/24/2016 15:30",
		"sTitle:" : "ShoYoshida 9/24/2016 15:30" } }
